Workbook
Name Aporte: Investimento!$E$14
Name Patrimonio: Investimento!$E$17
Name Qtd_Anos: Investimento!$E$15
Name Rendimento_Carteira: Investimento!$E$10
Name Salario: Investimento!$E$9
Name Sugestao_Investimento: Investimento!$E$11
Name Taxa_Mensal: Investimento!$E$16

Sheet Investimento
D8: CONFIGURAÇÕES
D9: Salário | E9: 5000
D10: Rendimento Carteira | E10: 0.006
D11: Sugestão de Investimento | E11: =E9*30% -> 1500
D13: INVESTIMENTO MENSAL
D14: Quanto investir por mês | E14: 500
D15: Por quantos anos | E15: 5
D16: Taxa de Rendimento Mensal | E16: 0.01079
D17: Patrimônio Acumulado | E17: =FV(Taxa_Mensal,Qtd_Anos*12,Aporte*-1) -> 41888.457
D18: Dividendos Mensais | E18: =Patrimonio*Rendimento_Carteira -> 251.33074
D20: CENÁRIOS | E20: PATRIMÔNIO | F20: DIVIDENDOS
A21: 2 | D21: Quanto em 2 anos | E21: =FV($E$16,$A21*12,$E$14*-1) -> 13613.814 | F21: =E21*Rendimento_Carteira -> 81.682882
A22: 5 | D22: Quanto em 5 anos | E22: =FV($E$16,$A22*12,$E$14*-1) -> 41888.457 | F22: =E22*Rendimento_Carteira -> 251.33074
A23: 10 | D23: Quanto em 10 anos | E23: =FV($E$16,$A23*12,$E$14*-1) -> 121642.11 | F23: =E23*Rendimento_Carteira -> 729.85264
A24: 20 | D24: Quanto em 20 anos | E24: =FV($E$16,$A24*12,$E$14*-1) -> 562599.2 | F24: =E24*Rendimento_Carteira -> 3375.5952
A25: 30 | D25: Quanto em 30 anos | E25: =FV($E$16,$A25*12,$E$14*-1) -> 2161084.8 | F25: =E25*Rendimento_Carteira -> 12966.509
D28: Perfil | F28: Conservador
D29: Valor a ser Investido por mês | F29: =Aporte -> 500
D31: TIPO DE FII | E31: % | F31: R$
D32: PAPEL | E32: =VLOOKUP($F$28&"-"&D32,Base!A:D,4,0) -> 0.3 | F32: =E32*$F$29 -> 150
D33: TIJOLO | E33: =VLOOKUP($F$28&"-"&D33,Base!A:D,4,0) -> 0.5 | F33: =E33*$F$29 -> 250
D34: HÍBRIDOS | E34: =VLOOKUP($F$28&"-"&D34,Base!A:D,4,0) -> 0.1 | F34: =E34*$F$29 -> 50
D35: FOFS | E35: =VLOOKUP($F$28&"-"&D35,Base!A:D,4,0) -> 0.1 | F35: =E35*$F$29 -> 50
D36: DESENVOLVIMENTO | E36: =VLOOKUP($F$28&"-"&D36,Base!A:D,4,0) -> 0 | F36: =E36*$F$29 -> 0
D37: HOTELARIAS | E37: =VLOOKUP($F$28&"-"&D37,Base!A:D,4,0) -> 0 | F37: =E37*$F$29 -> 0
F38: =SUM(F32:F37) -> 500

Sheet Base
A2: CHAVE | B2: PERFIL | C2: TIPO DE FII | D2: %
A3: =B3&"-"&C3 -> Conservador-PAPEL | B3: Conservador | C3: PAPEL | D3: 0.3
A4: =B4&"-"&C4 -> Conservador-TIJOLO | B4: Conservador | C4: TIJOLO | D4: 0.5
A5: =B5&"-"&C5 -> Conservador-HÍBRIDOS | B5: Conservador | C5: HÍBRIDOS | D5: 0.1
A6: =B6&"-"&C6 -> Conservador-FOFS | B6: Conservador | C6: FOFS | D6: 0.1
A7: =B7&"-"&C7 -> Conservador-DESENVOLVIMENTO | B7: Conservador | C7: DESENVOLVIMENTO | D7: 0
A8: =B8&"-"&C8 -> Conservador-HOTELARIAS | B8: Conservador | C8: HOTELARIAS | D8: 0
A9: =B9&"-"&C9 -> Moderado-PAPEL | B9: Moderado | C9: PAPEL | D9: 0.32
A10: =B10&"-"&C10 -> Moderado-TIJOLO | B10: Moderado | C10: TIJOLO | D10: 0.35
A11: =B11&"-"&C11 -> Moderado-HÍBRIDOS | B11: Moderado | C11: HÍBRIDOS | D11: 0.08
A12: =B12&"-"&C12 -> Moderado-FOFS | B12: Moderado | C12: FOFS | D12: 0.05
A13: =B13&"-"&C13 -> Moderado-DESENVOLVIMENTO | B13: Moderado | C13: DESENVOLVIMENTO | D13: 0.1
A14: =B14&"-"&C14 -> Moderado-HOTELARIAS | B14: Moderado | C14: HOTELARIAS | D14: 0.1
... A20: =B20&"-"&C20 -> Agressivo-HOTELARIAS | B20: Agressivo | C20: HOTELARIAS | D20: 0.1
